{
  "games": {
    "achievments.json": {
      "13": 91.1,
      "145": 82.7,
      "85": 82.2,
      "14": 81.9,
      "80": 80.3,
      "4": 75.4,
      "166": 75.3,
      "6": 75.3,
      "5": 75.3,
      "134": 74.7,
      "79": 71.4,
      "7": 70.9,
      "163": 70.2,
      "158": 70.2,
      "1": 70.2,
      "2": 69,
      "151": 68.7,
      "42": 67.6,
      "28": 67,
      "146": 66.5,
      "22": 66.2,
      "81": 65.1,
      "87": 64.8,
      "77": 64.5,
      "86": 62.8,
      "142": 60.9,
      "150": 60.6,
      "31": 60.1,
      "135": 59.7,
      "143": 59,
      "67": 58.7,
      "159": 57.6,
      "37": 57.6,
      "8": 57.6,
      "88": 56.9,
      "15": 56.1,
      "139": 55.3,
      "26": 55.3,
      "35": 55.1,
      "3": 54.4,
      "61": 54.2,
      "161": 54,
      "65": 53.9,
      "16": 53.9,
      "33": 53.5,
      "274": 53.3,
      "273": 53.3,
      "272": 53.3,
      "269": 53.3,
      "266": 53.3,
      "265": 53.3,
      "140": 51.9,
      "152": 51.4,
      "141": 50.5,
      "36": 49.4,
      "10": 49.4,
      "162": 48.5,
      "11": 48.3,
      "18": 47.9,
      "32": 47.4,
      "17": 47.3,
      "160": 46.6,
      "157": 46.5,
      "34": 46.5,
      "24": 46.4,
      "136": 45.3,
      "178": 45.2,
      "9": 44.3,
      "66": 44,
      "43": 44,
      "25": 43.7,
      "23": 43.6,
      "27": 43.1,
      "127": 42.7,
      "12": 42.5,
      "153": 41.5,
      "30": 41.2,
      "155": 41.1,
      "106": 40.7,
      "147": 39.8,
      "234": 39.3,
      "57": 39.3,
      "78": 39.2,
      "267": 38.8,
      "126": 38.7,
      "70": 38.6,
      "58": 37.6,
      "40": 37,
      "165": 36.7,
      "167": 36.6,
      "102": 36.3,
      "38": 36.1,
      "29": 35.7,
      "199": 34.9,
      "278": 34.7,
      "242": 34.5,
      "41": 34.2,
      "271": 34.1,
      "90": 34,
      "49": 33.9,
      "172": 33.4,
      "68": 33.4,
      "148": 33.2,
      "39": 33.1,
      "270": 32.9,
      "107": 32.7,
      "89": 32.6,
      "101": 32.4,
      "72": 32.3,
      "149": 32.1,
      "21": 31.7,
      "46": 31.6,
      "243": 31.3,
      "121": 31.2,
      "144": 30.6,
      "128": 30.6,
      "64": 30.6,
      "54": 29.7,
      "93": 29.5,
      "83": 29.4,
      "20": 29.4,
      "137": 29.3,
      "192": 29.1,
      "350": 29,
      "122": 29,
      "244": 28.8,
      "108": 28.8,
      "170": 28.6,
      "47": 28.4,
      "268": 28.3,
      "56": 28.2,
      "171": 28.1,
      "45": 28.1,
      "279": 27.7,
      "110": 27.5,
      "376": 27.4,
      "76": 27.3,
      "173": 27,
      "351": 26.9,
      "176": 26.9,
      "116": 26.9,
      "168": 26.7,
      "75": 26.5,
      "245": 26.4,
      "125": 26.4,
      "123": 26.3,
      "115": 26.3,
      "277": 26.1,
      "97": 26.1,
      "177": 26,
      "44": 26,
      "117": 25.9,
      "179": 25.5,
      "383": 25.2,
      "280": 25.2,
      "113": 25,
      "103": 25,
      "91": 24.9,
      "55": 24.9,
      "50": 24.9,
      "281": 24.8,
      "104": 24.8,
      "174": 24.7,
      "169": 24.7,
      "109": 24.7,
      "52": 24.5,
      "342": 24.4,
      "355": 24.3,
      "246": 24.3,
      "362": 24.1,
      "53": 24,
      "48": 23.8,
      "203": 23.7,
      "195": 23.7,
      "112": 23.6,
      "92": 23.6,
      "118": 23.5,
      "98": 23.5,
      "51": 23.4,
      "194": 23.3,
      "63": 23.3,
      "328": 23.2,
      "154": 23.2,
      "372": 23.1,
      "343": 23.1,
      "105": 23.1,
      "371": 23,
      "186": 22.7,
      "381": 22.6,
      "124": 22.6,
      "364": 22.4,
      "71": 22,
      "344": 21.9,
      "114": 21.9,
      "348": 21.8,
      "100": 21.8,
      "74": 21.8,
      "198": 21.7,
      "205": 21.6,
      "82": 21.6,
      "320": 21.4,
      "374": 21.3,
      "193": 21.2,
      "388": 21,
      "111": 21,
      "201": 20.8,
      "375": 20.7,
      "358": 20.7,
      "94": 20.7,
      "365": 20.6,
      "349": 20.5,
      "19": 20.5,
      "247": 20.4,
      "119": 20.4,
      "96": 20.4,
      "380": 20.3,
      "73": 20.1,
      "345": 19.8,
      "368": 19.7,
      "200": 19.3,
      "182": 19.3,
      "197": 19.2,
      "338": 19,
      "164": 19,
      "346": 18.9,
      "330": 18.7,
      "218": 18.6,
      "62": 18.6,
      "340": 18.5,
      "95": 18.3,
      "120": 18.2,
      "59": 18.1,
      "181": 18,
      "223": 17.9,
      "224": 17.9,
      "357": 17.8,
      "212": 17.8,
      "359": 17.6,
      "324": 17.6,
      "188": 17.6,
      "248": 17.4,
      "196": 17.4,
      "373": 17.3,
      "356": 17.3,
      "99": 17.2,
      "138": 17.1,
      "60": 16.9,
      "370": 16.6,
      "219": 16.6,
      "352": 16.3,
      "220": 16.3,
      "180": 16.3,
      "347": 16.2,
      "185": 16.2,
      "208": 15.9,
      "222": 15.9,
      "184": 15.7,
      "183": 15.7,
      "379": 15.6,
      "175": 15.5,
      "249": 15.4,
      "207": 15.4,
      "129": 15.2,
      "282": 15.1,
      "214": 15.1,
      "228": 15.1,
      "187": 15.1,
      "131": 14.9,
      "353": 14.7,
      "253": 14.5,
      "231": 14.5,
      "190": 14.5,
      "250": 14.4,
      "130": 14.4,
      "310": 14.3,
      "206": 14.3,
      "387": 14.2,
      "221": 14.2,
      "233": 14.1,
      "318": 13.9,
      "211": 13.9,
      "132": 13.8,
      "251": 13.7,
      "275": 13.7,
      "335": 13.6,
      "209": 13.6,
      "133": 13.6,
      "229": 13.4,
      "341": 13.3,
      "322": 13.3,
      "226": 13.3,
      "312": 13.1,
      "213": 13.1,
      "210": 13,
      "259": 12.5,
      "216": 12.3,
      "232": 12.3,
      "311": 12.2,
      "227": 12.1,
      "363": 12,
      "258": 12,
      "296": 11.9,
      "290": 11.7,
      "156": 11.6,
      "314": 11.5,
      "263": 11.5,
      "189": 11.5,
      "332": 11.4,
      "225": 11.4,
      "285": 11.3,
      "369": 11.2,
      "329": 11.2,
      "261": 11.2,
      "202": 11.2,
      "331": 11,
      "315": 11,
      "313": 10.9,
      "256": 10.8,
      "321": 10.7,
      "254": 10.7,
      "389": 10.4,
      "377": 10.4,
      "69": 10.4,
      "289": 10.3,
      "284": 10.3,
      "262": 10.3,
      "215": 10.3,
      "241": 10.2,
      "384": 10.1,
      "236": 10.1,
      "204": 10.1,
      "378": 10,
      "255": 10,
      "316": 9.9,
      "317": 9.8,
      "299": 9.8,
      "295": 9.8,
      "283": 9.7,
      "238": 9.7,
      "257": 9.7,
      "252": 9.7,
      "391": 9.6,
      "390": 9.6,
      "304": 9.6,
      "230": 9.6,
      "298": 9.5,
      "260": 9.4,
      "306": 9.3,
      "287": 9.3,
      "240": 9.3,
      "367": 9.2,
      "237": 9.1,
      "191": 9.1,
      "288": 9,
      "297": 8.9,
      "291": 8.9,
      "286": 8.9,
      "217": 8.9,
      "303": 8.8,
      "239": 8.8,
      "382": 8.7,
      "301": 8.6,
      "333": 8.2,
      "84": 8.2,
      "309": 8.1,
      "302": 8.1,
      "292": 8,
      "326": 7.9,
      "305": 7.9,
      "393": 7.8,
      "360": 7.8,
      "300": 7.7,
      "264": 7.7,
      "276": 7.7,
      "392": 7.4,
      "395": 7.3,
      "337": 7.2,
      "293": 7,
      "307": 6.9,
      "394": 6.8,
      "397": 6.7,
      "308": 6.7,
      "399": 6.5,
      "334": 6.5,
      "398": 6.4,
      "396": 6.4,
      "319": 6.4,
      "403": 6.2,
      "323": 6.1,
      "401": 5.9,
      "294": 5.9,
      "235": 5.6,
      "400": 5.1,
      "361": 5.1,
      "402": 4.3,
      "385": 4.3,
      "327": 4.2,
      "325": 4.1,
      "336": 3.8,
      "366": 3.7,
      "386": 3.4,
      "339": 2.9,
      "354": 2.7
    },
    "350300": {},
    "1172310": {},
    "862220": {},
    "1166200": {},
    "1001200": {
      "ACHIEVEMENT_01": 50.3,
      "ACHIEVEMENT_02": 29.1,
      "ACHIEVEMENT_03": 23.6,
      "ACHIEVEMENT_05": 19.5,
      "ACHIEVEMENT_04": 19.2,
      "ACHIEVEMENT_06": 16.7,
      "ACHIEVEMENT_07": 12.1,
      "ACHIEVEMENT_08": 8.6
    },
    "1109460": {
      "achieve_startGame": 92.8,
      "achieve_CG1": 73.7,
      "achieve_CG2": 60.8,
      "achieve_CG3": 42.8,
      "achieve_CG4": 34.4,
      "achieve_CG5": 31.2,
      "achieve_CG6": 30.6
    },
    "836590": {
      "NEW_ACHIEVEMENT_1_12": 76.4,
      "NEW_ACHIEVEMENT_1_15": 65.7,
      "NEW_ACHIEVEMENT_1_1": 56.7,
      "NEW_ACHIEVEMENT_1_14": 56.1,
      "NEW_ACHIEVEMENT_1_11": 54.4,
      "NEW_ACHIEVEMENT_1_0": 47.1,
      "NEW_ACHIEVEMENT_1_3": 38.7,
      "NEW_ACHIEVEMENT_1_9": 25.2,
      "NEW_ACHIEVEMENT_1_4": 24.1,
      "NEW_ACHIEVEMENT_1_18": 23.5,
      "NEW_ACHIEVEMENT_1_19": 23,
      "NEW_ACHIEVEMENT_1_8": 23,
      "NEW_ACHIEVEMENT_1_13": 15.1,
      "NEW_ACHIEVEMENT_1_24": 12.9,
      "NEW_ACHIEVEMENT_1_21": 11.7,
      "NEW_ACHIEVEMENT_1_17": 10.6,
      "NEW_ACHIEVEMENT_1_10": 10.6,
      "NEW_ACHIEVEMENT_1_23": 6.7,
      "NEW_ACHIEVEMENT_1_22": 5.6,
      "NEW_ACHIEVEMENT_1_16": 3.9
    },
    "1166210": {},
    "1196400": {},
    "1178020": {},
    "756530": {
      "ACHIEVEMENT_01": 90,
      "ACHIEVEMENT_20": 72.8,
      "ACHIEVEMENT_21": 71.3,
      "ACHIEVEMENT_02": 67.2,
      "ACHIEVEMENT_13": 65.7,
      "ACHIEVEMENT_10": 62.1,
      "ACHIEVEMENT_03": 54.7,
      "ACHIEVEMENT_04": 48.4,
      "ACHIEVEMENT_11": 43.3,
      "ACHIEVEMENT_05": 42.9,
      "ACHIEVEMENT_16": 42.2,
      "ACHIEVEMENT_14": 41,
      "ACHIEVEMENT_06": 39.5,
      "ACHIEVEMENT_07": 36.5,
      "ACHIEVEMENT_08": 35.2,
      "ACHIEVEMENT_38": 34.8,
      "ACHIEVEMENT_09": 33.9,
      "ACHIEVEMENT_24": 33.8,
      "ACHIEVEMENT_23": 31.3,
      "ACHIEVEMENT_22": 30.9,
      "ACHIEVEMENT_12": 27.5,
      "ACHIEVEMENT_15": 24,
      "ACHIEVEMENT_32": 20.6,
      "ACHIEVEMENT_33": 17,
      "ACHIEVEMENT_25": 12.5,
      "ACHIEVEMENT_27": 11.1,
      "ACHIEVEMENT_19": 11.1,
      "ACHIEVEMENT_29": 7.1,
      "ACHIEVEMENT_31": 6.9,
      "ACHIEVEMENT_34": 6.7,
      "ACHIEVEMENT_30": 6.2,
      "ACHIEVEMENT_26": 2.7,
      "ACHIEVEMENT_28": 2.3,
      "ACHIEVEMENT_17": 2.3,
      "ACHIEVEMENT_35": 1.6,
      "ACHIEVEMENT_18": 1.6,
      "ACHIEVEMENT_36": 1.1,
      "ACHIEVEMENT_37": 0.8,
      "ACHIEVEMENT_00": 0.7
    },
    "1191450": {},
    "1132210": {},
    "254900": {},
    "865160": {},
    "1190410": {},
    "728530": {
      "TRIGGER_OF_SUCCESS": 89.9,
      "A_NEW_DOOR": 86.1,
      "ABILITY_LEVEL": 77.9,
      "STRAY_WARRIORS": 73.2,
      "SET_SAIL_FOR_TOMORROW": 72.1,
      "CENTRAL_DESIGN_DEPARTMENT": 70.5,
      "CHOSEN_PATH": 63.7,
      "DREAM_FRAGMENTS": 61.8,
      "EXCHANGING_FATES": 57.1,
      "SHIP_OF_HOPE": 39.3,
      "MOVEMENTS_TOWARDS_THE_FUTURE": 32,
      "RETURN_TO_FOREVER": 31.9,
      "A_FUTURE_THAT_NEVER_ENDS": 28.9,
      "THE_FINAL_VICTOR": 28.7,
      "VERITABLE_WARRIOR": 26.9,
      "BLADE_TO_THE_FUTURE": 25.8,
      "PATH_TO_PEACE": 25.7,
      "STARGAZER_STARCHASER": 24,
      "THE_FINAL_POWER": 21.4,
      "THOSE_WHO_WENT_ASTRAY": 21.4,
      "RETURN_REPORT": 20.7,
      "AFTER_COLONY": 20,
      "CHANGING_WORLD": 19,
      "THEIR_PLACE": 18,
      "BEYOND": 16.7,
      "FIELD_OF_BATTLE_FLOWERS": 15.7,
      "A_NEW_JOURNEY": 14.8,
      "MACHINE_TO_CHANGE_THE_WORLD": 14.6,
      "POST_DISASTER": 11.7,
      "ANNO_DOMINI": 11.6,
      "COSMIC_ERA": 11.6,
      "RESOLUTE_GUNFIRE": 7.5,
      "LEGENDARY_POWER": 6.9,
      "ENDING_THE_CONVERSATIONS": 5.5,
      "LIGHT_OF_PEACE_AND_HOPE": 5.2,
      "RECORDED_CALAMITY": 5.2,
      "DOOR_OF_REFORMATION": 3.7,
      "VESTIGES_OF_VICTORY_AND_DEFEAT": 3.4,
      "SD_GUNDAM_G_GENERATION_CROSS_RAYS": 2.2
    },
    "1186580": {
      "NEW_ACHIEVEMENT_1_0": 83.8,
      "NEW_ACHIEVEMENT_1_16": 73,
      "NEW_ACHIEVEMENT_1_1": 73,
      "NEW_ACHIEVEMENT_1_6": 46.9,
      "NEW_ACHIEVEMENT_1_8": 44.6,
      "NEW_ACHIEVEMENT_1_14": 43.8,
      "NEW_ACHIEVEMENT_1_12": 43,
      "NEW_ACHIEVEMENT_1_5": 37.6,
      "NEW_ACHIEVEMENT_1_7": 36.9,
      "NEW_ACHIEVEMENT_1_9": 34.6,
      "NEW_ACHIEVEMENT_1_3": 28.4,
      "NEW_ACHIEVEMENT_1_19": 23,
      "NEW_ACHIEVEMENT_1_18": 23,
      "NEW_ACHIEVEMENT_1_4": 23,
      "NEW_ACHIEVEMENT_1_10": 20.7,
      "NEW_ACHIEVEMENT_1_15": 18.4,
      "NEW_ACHIEVEMENT_1_2": 18.4,
      "NEW_ACHIEVEMENT_1_11": 14.6,
      "NEW_ACHIEVEMENT_1_20": 11.5,
      "NEW_ACHIEVEMENT_1_17": 11.5,
      "NEW_ACHIEVEMENT_1_13": 10.7,
      "NEW_ACHIEVEMENT_1_21": 6.9
    },
    "1185950": {},
    "1178120": {
      "ACH_FUSION": 96.1,
      "ACH_NEWBIE": 95.4,
      "ACH_NOT_ALONE": 94.3,
      "ACH_HEALTHIEST": 93.7,
      "ACH_DECENT": 92.2,
      "ACH_THREE_SOME": 92,
      "ACH_LITTLE_KING": 92,
      "ACH_GREAT_CRAB": 88,
      "ACH_HEAVY": 78.5,
      "ACH_BORN": 75,
      "ACH_SEMI_PRO": 67.2,
      "ACH_GHOST": 64.8,
      "ACH_STRONG": 63.3,
      "ACH_DRAGON": 26.7,
      "ACH_ABOM": 25.3,
      "ACH_TOTALLY_FAB": 11.7,
      "ACH_FAMILY_FIRST": 4.9
    },
    "696120": {},
    "1190150": {},
    "1103800": {},
    "616920": {},
    "1193570": {},
    "1052440": {
      "CROIXLEUR_ACHIEVEMENT_001": 89.2,
      "CROIXLEUR_ACHIEVEMENT_020": 80.9,
      "CROIXLEUR_ACHIEVEMENT_014": 73.4,
      "CROIXLEUR_ACHIEVEMENT_030": 69.2,
      "CROIXLEUR_ACHIEVEMENT_017": 61.5,
      "CROIXLEUR_ACHIEVEMENT_002": 48.6,
      "CROIXLEUR_ACHIEVEMENT_027": 42.9,
      "CROIXLEUR_ACHIEVEMENT_031": 31.4,
      "CROIXLEUR_ACHIEVEMENT_015": 26.9,
      "CROIXLEUR_ACHIEVEMENT_018": 19.7,
      "CROIXLEUR_ACHIEVEMENT_033": 19.3,
      "CROIXLEUR_ACHIEVEMENT_021": 17.3,
      "CROIXLEUR_ACHIEVEMENT_003": 16.5,
      "CROIXLEUR_ACHIEVEMENT_028": 15.2,
      "CROIXLEUR_ACHIEVEMENT_005": 13.1,
      "CROIXLEUR_ACHIEVEMENT_011": 11,
      "CROIXLEUR_ACHIEVEMENT_035": 10.4,
      "CROIXLEUR_ACHIEVEMENT_032": 8.7,
      "CROIXLEUR_ACHIEVEMENT_029": 8,
      "CROIXLEUR_ACHIEVEMENT_022": 7.9,
      "CROIXLEUR_ACHIEVEMENT_023": 7.2,
      "CROIXLEUR_ACHIEVEMENT_006": 7.2,
      "CROIXLEUR_ACHIEVEMENT_034": 7,
      "CROIXLEUR_ACHIEVEMENT_004": 5.8,
      "CROIXLEUR_ACHIEVEMENT_043": 5.7,
      "CROIXLEUR_ACHIEVEMENT_039": 4.9,
      "CROIXLEUR_ACHIEVEMENT_007": 4.9,
      "CROIXLEUR_ACHIEVEMENT_044": 4.5,
      "CROIXLEUR_ACHIEVEMENT_019": 4.4,
      "CROIXLEUR_ACHIEVEMENT_025": 4.1,
      "CROIXLEUR_ACHIEVEMENT_037": 3.7,
      "CROIXLEUR_ACHIEVEMENT_024": 3.4,
      "CROIXLEUR_ACHIEVEMENT_008": 3.3,
      "CROIXLEUR_ACHIEVEMENT_016": 2.9,
      "CROIXLEUR_ACHIEVEMENT_040": 2.7,
      "CROIXLEUR_ACHIEVEMENT_012": 2.4,
      "CROIXLEUR_ACHIEVEMENT_041": 2.2,
      "CROIXLEUR_ACHIEVEMENT_009": 2.1,
      "CROIXLEUR_ACHIEVEMENT_013": 1.9,
      "CROIXLEUR_ACHIEVEMENT_036": 1.7,
      "CROIXLEUR_ACHIEVEMENT_038": 1.5,
      "CROIXLEUR_ACHIEVEMENT_026": 1.5,
      "CROIXLEUR_ACHIEVEMENT_010": 1.3,
      "CROIXLEUR_ACHIEVEMENT_042": 1.1,
      "CROIXLEUR_ACHIEVEMENT_045": 1,
      "CROIXLEUR_ACHIEVEMENT_000": 0.9
    },
    "1182720": {
      "COMPLETED_LEVEL_02": 44.4,
      "COMPLETED_LEVEL_01": 44.4,
      "COMPLETED_LEVEL_10": 22.2,
      "COMPLETED_LEVEL_09": 22.2,
      "COMPLETED_LEVEL_08": 22.2,
      "COMPLETED_LEVEL_07": 22.2,
      "COMPLETED_LEVEL_06": 22.2,
      "COMPLETED_LEVEL_05": 22.2,
      "COMPLETED_LEVEL_04": 22.2,
      "COMPLETED_LEVEL_03": 22.2
    },
    "1052430": {
      "ACHIEVEMENT_NAME_1": 0
    },
    "1048020": {
      "BigHarvest": 59.2,
      "GrowingUpToo": 48.1,
      "Foreigners": 44.4,
      "LastChance": 37,
      "StillMore": 37,
      "LighthouseShining": 33.3,
      "LighthouseShiningFaintly": 33.3,
      "FishinaBattleForLongPeriod": 33.3,
      "HayParty": 33.3,
      "HarvestMaster": 29.6,
      "FreezingFarm": 29.6,
      "UnluckyPeople": 29.6,
      "LighthouseRegainedLight": 29.6,
      "FarmFestival": 29.6,
      "MoreBiggerHarvest": 29.6,
      "JustTheBeginning": 29.6,
      "CameAboutHalf": 29.6,
      "LighthouseIsFar": 29.6,
      "YesLetsGoToBeach": 29.6,
      "GroovyKorpokkur": 25.9,
      "ArrivedLighthouse": 25.9,
      "TheLastDangerousWay": 25.9,
      "FromHeavensToGround": 25.9,
      "SeeTheLighthouse": 25.9,
      "BigTropicalJuice": 22.2,
      "RanThroughAllTheIslands": 22.2,
      "SurprisinglyBigHarvest": 18.5
    },
    "254940": {},
    "756890": {},
    "1109840": {
      "56": 66.6,
      "1": 61.1,
      "28": 55.5,
      "66": 50,
      "37": 38.8,
      "3": 33.3,
      "2": 33.3,
      "4": 27.7,
      "60": 22.2,
      "29": 22.2,
      "10": 22.2,
      "9": 22.2,
      "8": 22.2,
      "7": 22.2,
      "6": 22.2,
      "5": 22.2,
      "67": 16.6,
      "57": 16.6,
      "40": 16.6,
      "38": 16.6,
      "33": 16.6,
      "14": 16.6,
      "13": 16.6,
      "12": 16.6,
      "11": 16.6,
      "80": 11.1,
      "62": 11.1,
      "61": 11.1,
      "41": 11.1,
      "22": 11.1,
      "21": 11.1,
      "20": 11.1,
      "19": 11.1,
      "18": 11.1,
      "17": 11.1,
      "16": 11.1,
      "15": 11.1,
      "79": 5.5,
      "78": 5.5,
      "77": 5.5,
      "76": 5.5,
      "75": 5.5,
      "74": 5.5,
      "73": 5.5,
      "72": 5.5,
      "71": 5.5,
      "70": 5.5,
      "69": 5.5,
      "65": 5.5,
      "64": 5.5,
      "63": 5.5,
      "59": 5.5,
      "58": 5.5,
      "45": 5.5,
      "44": 5.5,
      "43": 5.5,
      "42": 5.5,
      "39": 5.5,
      "36": 5.5,
      "35": 5.5,
      "34": 5.5,
      "32": 5.5,
      "31": 5.5,
      "30": 5.5,
      "27": 5.5,
      "26": 5.5,
      "25": 5.5,
      "24": 5.5,
      "23": 5.5,
      "68": 0,
      "49": 0,
      "48": 0,
      "47": 0,
      "46": 0
    },
    "1102940": {},
    "1193550": {},
    "951680": {
      "ID_TUTORIAL_COMPLETED": 54.3,
      "ID_CAMPAIGN_LEVEL_ONE": 23.4,
      "ID_WIN_2_PASSPLAY": 19.7,
      "ID_CAMPAIGN_LEVEL_TWO": 11.7,
      "ID_CAMPAIGN_LEVEL_THREE": 5.5,
      "ID_WIN_4_PASSPLAY": 5.5,
      "ID_WIN_3_PASSPLAY": 5.5,
      "ID_CAMPAIGN_LEVEL_FOUR": 4.9,
      "ID_CAMPAIGN_COMPLETE": 4.3,
      "ID_WIN_2_ONLINE": 4.3,
      "ID_CAMPAIGN_MAX_SCORE": 2.4,
      "ID_CAMPAIGN_LEVEL_FIVE": 2.4,
      "ID_BUDDY_HUNTER": 1.2,
      "ID_WIN_4_ONLINE": 0.6,
      "ID_WIN_3_ONLINE": 0.6
    },
    "1156980": {
      "ACH1": 78.1,
      "ACH2": 75,
      "ACH4": 65.6,
      "ACH3": 65.6,
      "ACH5": 62.5,
      "ACH6": 59.3,
      "ACH7": 53.1,
      "ACH10": 50,
      "ACH9": 50,
      "ACH8": 50,
      "ACH15": 46.8,
      "ACH14": 46.8,
      "ACH13": 46.8,
      "ACH12": 46.8,
      "ACH11": 46.8,
      "ACH22": 43.7,
      "ACH21": 43.7,
      "ACH20": 43.7,
      "ACH19": 43.7,
      "ACH18": 43.7,
      "ACH17": 43.7,
      "ACH16": 43.7,
      "ACH28": 40.6,
      "ACH27": 40.6,
      "ACH26": 40.6,
      "ACH25": 40.6,
      "ACH24": 40.6,
      "ACH23": 40.6
    },
    "1165860": {
      "first": 89.6,
      "1": 82.5,
      "2": 76.9,
      "3": 69.9,
      "4": 63.3,
      "5": 59.5,
      "6": 54.6,
      "7": 51.7,
      "8": 49.5,
      "9": 47.2,
      "10": 44.8,
      "11": 43,
      "12": 41.3,
      "13": 38.6,
      "14": 37.6,
      "15": 36.2,
      "16": 35.6,
      "17": 34.9,
      "18": 33.7,
      "19": 32.6,
      "20": 31.4,
      "21": 29.7,
      "22": 29.2,
      "23": 28.9,
      "24": 28,
      "25": 26.9,
      "26": 26.6,
      "mask_dude": 26.4,
      "27": 25.8,
      "28": 25.2,
      "pink_man": 25,
      "29": 24.4,
      "30": 24.3,
      "31": 23.9,
      "virtual_guy": 23,
      "32": 22.9,
      "33": 22.4,
      "34": 22.1,
      "35": 21.5,
      "36": 21,
      "37": 20.7,
      "39": 20.4,
      "38": 20.4,
      "41": 19.8,
      "40": 19.8,
      "42": 19.6,
      "43": 19.5,
      "44": 19.1,
      "45": 18.8,
      "46": 18.7,
      "48": 18.5,
      "47": 18.5,
      "49": 18.1
    },
    "1191680": {},
    "898430": {
      "Achivement_World_Forest": 72.3,
      "Achivement_World_Mountain": 38.2,
      "Achivement_Defeat_BeastMan": 31.9,
      "Achivement_World_TropicallsIslands": 31.9,
      "Achivement_World_DistantSea": 27.6,
      "Achivement_World_FairtyTale": 27.6,
      "Achivement_Defeat_Phoenix": 23.4,
      "Achivement_Person_ViewLord": 23.4,
      "Achivement_World_Taiga": 23.4,
      "Achivement_World_Desert": 23.4,
      "Achivement_World_SkyIslands": 21.2,
      "Achivement_Defeat_Hell": 19.1,
      "Achivement_World_Hades": 19.1,
      "Achivement_Defeat_ChimeraSnake": 17,
      "Achivement_Defeat_ChimeraGoat": 17,
      "Achivement_Defeat_ChimeraLion": 17,
      "Achivement_Defeat_DarkDragon": 14.8,
      "Achivement_Defeat_Pharaoh": 14.8,
      "Achivement_World_Hellscape": 14.8,
      "Achivement_World_Cave": 14.8,
      "Achivement_Defeat_Kraken": 12.7,
      "Achivement_Defeat_Saurus": 12.7,
      "Achivement_All_Clear": 10.6,
      "Achivement_Defeat_Ogreking": 10.6,
      "Achivement_Defeat_IronGolem": 10.6,
      "Achivement_Defeat_Unicorn": 10.6
    },
    "1192740": {
      "NEW_ACHIEVEMENT_1_0": 96.7,
      "NEW_ACHIEVEMENT_1_1": 86.3,
      "NEW_ACHIEVEMENT_1_2": 80.7,
      "NEW_ACHIEVEMENT_1_3": 76.9,
      "NEW_ACHIEVEMENT_1_4": 71.8,
      "NEW_ACHIEVEMENT_1_5": 65.7,
      "NEW_ACHIEVEMENT_1_6": 58.6,
      "NEW_ACHIEVEMENT_1_7": 55.8,
      "NEW_ACHIEVEMENT_1_8": 52.5,
      "NEW_ACHIEVEMENT_1_9": 47.8,
      "NEW_ACHIEVEMENT_1_10": 43.1,
      "NEW_ACHIEVEMENT_1_11": 39.9,
      "NEW_ACHIEVEMENT_1_12": 39.4,
      "NEW_ACHIEVEMENT_1_13": 38.9,
      "NEW_ACHIEVEMENT_1_16": 37.5,
      "NEW_ACHIEVEMENT_1_15": 37.5,
      "NEW_ACHIEVEMENT_1_14": 37.5,
      "NEW_ACHIEVEMENT_1_17": 37,
      "NEW_ACHIEVEMENT_1_18": 34.7,
      "NEW_ACHIEVEMENT_1_20": 32.8,
      "NEW_ACHIEVEMENT_1_19": 32.8,
      "NEW_ACHIEVEMENT_1_21": 31.4,
      "NEW_ACHIEVEMENT_1_22": 30.5,
      "NEW_ACHIEVEMENT_1_23": 30,
      "NEW_ACHIEVEMENT_1_26": 29.5,
      "NEW_ACHIEVEMENT_1_25": 29.5,
      "NEW_ACHIEVEMENT_1_24": 29.5,
      "NEW_ACHIEVEMENT_1_27": 29.1,
      "NEW_ACHIEVEMENT_2_18": 28.6,
      "NEW_ACHIEVEMENT_2_17": 28.6,
      "NEW_ACHIEVEMENT_2_16": 28.6,
      "NEW_ACHIEVEMENT_2_14": 28.6,
      "NEW_ACHIEVEMENT_2_13": 28.6,
      "NEW_ACHIEVEMENT_2_12": 28.6,
      "NEW_ACHIEVEMENT_2_11": 28.6,
      "NEW_ACHIEVEMENT_2_10": 28.6,
      "NEW_ACHIEVEMENT_2_9": 28.6,
      "NEW_ACHIEVEMENT_2_8": 28.6,
      "NEW_ACHIEVEMENT_2_7": 28.6,
      "NEW_ACHIEVEMENT_2_6": 28.6,
      "NEW_ACHIEVEMENT_2_3": 28.6,
      "NEW_ACHIEVEMENT_2_2": 28.6,
      "NEW_ACHIEVEMENT_2_1": 28.6,
      "NEW_ACHIEVEMENT_2_0": 28.6,
      "NEW_ACHIEVEMENT_1_31": 28.6,
      "NEW_ACHIEVEMENT_1_30": 28.6,
      "NEW_ACHIEVEMENT_1_29": 28.6,
      "NEW_ACHIEVEMENT_1_28": 28.6,
      "NEW_ACHIEVEMENT_2_19": 28.1,
      "NEW_ACHIEVEMENT_2_15": 28.1,
      "NEW_ACHIEVEMENT_2_5": 28.1,
      "NEW_ACHIEVEMENT_2_4": 28.1,
      "NEW_ACHIEVEMENT_2_20": 27.6
    },
    "1165850": {},
    "1181440": {},
    "1198060": {},
    "1179480": {},
    "1194380": {},
    "1171140": {
      "Sniper_1": 51.8,
      "Lethal_Agent_1": 48.1,
      "Courier_1": 48,
      "Upgrader_1": 47,
      "Skillful_1": 34.7,
      "Sniper_2": 22.4,
      "Winner_1": 21.4,
      "Upgrader_2": 18.9,
      "Lethal_Agent_2": 18.4,
      "Attachment_Unlocked_1": 18,
      "Skillful_2": 17.9,
      "Courier_2": 17.5,
      "Sniper_3": 13.3,
      "Skillful_3": 12.9,
      "Winner_2": 11.8,
      "Lethal_Agent_3": 10.5,
      "Consumer_1": 10.4,
      "Courier_3": 9.5,
      "Upgrader_3": 9.5,
      "Sniper_4": 8,
      "Skillful_4": 7.8,
      "Consumer_2": 7.3,
      "Winner_3": 6.6,
      "Lethal_Agent_4": 6.1,
      "Consumer_3": 5.3,
      "Skillful_5": 5.1,
      "Veteran_Agent": 5.1,
      "Courier_4": 5,
      "Lethal_Agent_5": 4.3,
      "Sniper_5": 3.9,
      "Lots_of_Guns_1": 3.7,
      "Skillful_6": 3.4,
      "Lethal_Agent_6": 3.3,
      "Consumer_4": 3.2,
      "Attachment_Unlocked_2": 3.1,
      "Winner_4": 3,
      "Lethal_Agent_7": 2.7,
      "Skillful_7": 2.6,
      "Skillful_8": 2.2,
      "Upgrader_4": 2.2,
      "Sniper_6": 2.2,
      "Courier_5": 2,
      "Skillful_9": 1.9,
      "Consumer_5": 1.9,
      "Lots_of_Guns_2": 1.8,
      "Skillful_10": 1.7,
      "Skillful_11": 1.5,
      "Sniper_7": 1.5,
      "Winner_5": 1.5,
      "Lethal_Agent_8": 1.4,
      "Skillful_13": 1.3,
      "Skillful_12": 1.3,
      "Havoc_Unleashed": 1.2,
      "Axiom_Unleashed": 1.2,
      "Skillful_14": 1.1,
      "Attachment_Unlocked_3": 1.1,
      "Sniper_8": 1.1,
      "Courier_6": 1,
      "Consumer_6": 1,
      "Winner_6": 1,
      "Upgrader_5": 0.8,
      "Lethal_Agent_9": 0.8,
      "Winner_7": 0.8,
      "Consumer_7": 0.7,
      "Courier_7": 0.6,
      "Consumer_9": 0.6,
      "Consumer_8": 0.6,
      "Lots_of_Guns_3": 0.6,
      "Master_Agent": 0.6,
      "Winner_8": 0.6,
      "Consumer_13": 0.5,
      "Consumer_12": 0.5,
      "Consumer_11": 0.5,
      "Consumer_10": 0.5,
      "Upgrader_6": 0.5,
      "Lethal_Agent_10": 0.5,
      "Consumer_14": 0.4,
      "Attachment_Unlocked_5": 0.4,
      "Attachment_Unlocked_4": 0.4,
      "Lots_of_Guns_5": 0.4,
      "Lots_of_Guns_4": 0.4,
      "Upgrader_8": 0.4,
      "Upgrader_7": 0.4
    },
    "1194620": {
      "ach_5": 76.1,
      "ach_10": 66.6,
      "ach_speed": 61.9,
      "ach_15": 57.1,
      "ach_lives": 52.3,
      "ach_20": 52.3,
      "ach_size": 47.6,
      "ach_25": 47.6,
      "ach_30": 42.8,
      "ach_veryeasy": 38,
      "ach_33": 38,
      "ach_gold": 33.3,
      "ach_nosize": 19,
      "ach_normal": 19,
      "ach_hard": 19,
      "ach_easy": 19
    },
    "1184780": {
      "NEW_ACHIEVEMENT_3_0": 65,
      "NEW_ACHIEVEMENT_3_12": 40,
      "NEW_ACHIEVEMENT_3_9": 40,
      "NEW_ACHIEVEMENT_3_6": 40,
      "NEW_ACHIEVEMENT_3_10": 20,
      "NEW_ACHIEVEMENT_3_13": 17.5,
      "NEW_ACHIEVEMENT_3_1": 15,
      "NEW_ACHIEVEMENT_3_7": 10,
      "NEW_ACHIEVEMENT_3_14": 5,
      "NEW_ACHIEVEMENT_3_11": 5,
      "NEW_ACHIEVEMENT_3_2": 5,
      "NEW_ACHIEVEMENT_3_8": 0,
      "NEW_ACHIEVEMENT_3_5": 0,
      "NEW_ACHIEVEMENT_3_4": 0,
      "NEW_ACHIEVEMENT_3_3": 0
    },
    "1066030": {
      "ACH_1": 40.3,
      "ACH_2": 19.2,
      "ACH_3": 14.9,
      "ACH_4": 11.4,
      "ACH_5": 7.8,
      "ACH_7": 2.6,
      "ACH_6": 2.6,
      "ACH_37": 1.7,
      "ACH_35": 1.7,
      "ACH_10": 1.7,
      "ACH_9": 1.7,
      "ACH_8": 1.7,
      "ACH_0": 1.7,
      "ACH_47": 0.8,
      "ACH_46": 0.8,
      "ACH_45": 0.8,
      "ACH_44": 0.8,
      "ACH_43": 0.8,
      "ACH_42": 0.8,
      "ACH_41": 0.8,
      "ACH_40": 0.8,
      "ACH_39": 0.8,
      "ACH_38": 0.8,
      "ACH_36": 0.8,
      "ACH_34": 0.8,
      "ACH_33": 0.8,
      "ACH_32": 0.8,
      "ACH_31": 0.8,
      "ACH_30": 0.8,
      "ACH_29": 0.8,
      "ACH_28": 0.8,
      "ACH_27": 0.8,
      "ACH_26": 0.8,
      "ACH_25": 0.8,
      "ACH_24": 0.8,
      "ACH_23": 0.8,
      "ACH_22": 0.8,
      "ACH_21": 0.8,
      "ACH_20": 0.8,
      "ACH_19": 0.8,
      "ACH_18": 0.8,
      "ACH_17": 0.8,
      "ACH_16": 0.8,
      "ACH_15": 0.8,
      "ACH_14": 0.8,
      "ACH_13": 0.8,
      "ACH_12": 0.8,
      "ACH_11": 0.8
    },
    "1113880": {},
    "1147670": {},
    "250900": {
      "13": 91.1,
      "145": 82.7,
      "85": 82.2,
      "14": 81.9,
      "80": 80.3,
      "4": 75.4,
      "166": 75.3,
      "6": 75.3,
      "5": 75.3,
      "134": 74.7,
      "79": 71.4,
      "7": 70.9,
      "163": 70.2,
      "158": 70.2,
      "1": 70.2,
      "2": 69,
      "151": 68.7,
      "42": 67.6,
      "28": 67,
      "146": 66.5,
      "22": 66.2,
      "81": 65.1,
      "87": 64.8,
      "77": 64.5,
      "86": 62.8,
      "142": 60.9,
      "150": 60.6,
      "31": 60.1,
      "135": 59.7,
      "143": 59,
      "67": 58.7,
      "159": 57.6,
      "37": 57.6,
      "8": 57.6,
      "88": 56.9,
      "15": 56.1,
      "139": 55.3,
      "26": 55.3,
      "35": 55.1,
      "3": 54.4,
      "61": 54.2,
      "161": 54,
      "65": 53.9,
      "16": 53.9,
      "33": 53.5,
      "274": 53.3,
      "273": 53.3,
      "272": 53.3,
      "269": 53.3,
      "266": 53.3,
      "265": 53.3,
      "140": 51.9,
      "152": 51.4,
      "141": 50.5,
      "36": 49.4,
      "10": 49.4,
      "162": 48.5,
      "11": 48.3,
      "18": 47.9,
      "32": 47.4,
      "17": 47.3,
      "160": 46.6,
      "157": 46.5,
      "34": 46.5,
      "24": 46.4,
      "136": 45.3,
      "178": 45.2,
      "9": 44.3,
      "66": 44,
      "43": 44,
      "25": 43.7,
      "23": 43.6,
      "27": 43.1,
      "127": 42.7,
      "12": 42.5,
      "153": 41.5,
      "30": 41.2,
      "155": 41.1,
      "106": 40.7,
      "147": 39.8,
      "234": 39.3,
      "57": 39.3,
      "78": 39.2,
      "267": 38.8,
      "126": 38.7,
      "70": 38.6,
      "58": 37.6,
      "40": 37,
      "165": 36.7,
      "167": 36.6,
      "102": 36.3,
      "38": 36.1,
      "29": 35.7,
      "199": 34.9,
      "278": 34.7,
      "242": 34.5,
      "41": 34.2,
      "271": 34.1,
      "90": 34,
      "49": 33.9,
      "172": 33.4,
      "68": 33.4,
      "148": 33.2,
      "39": 33.1,
      "270": 32.9,
      "107": 32.7,
      "89": 32.6,
      "101": 32.4,
      "72": 32.3,
      "149": 32.1,
      "21": 31.7,
      "46": 31.6,
      "243": 31.3,
      "121": 31.2,
      "144": 30.6,
      "128": 30.6,
      "64": 30.6,
      "54": 29.7,
      "93": 29.5,
      "83": 29.4,
      "20": 29.4,
      "137": 29.3,
      "192": 29.1,
      "350": 29,
      "122": 29,
      "244": 28.8,
      "108": 28.8,
      "170": 28.6,
      "47": 28.4,
      "268": 28.3,
      "56": 28.2,
      "171": 28.1,
      "45": 28.1,
      "279": 27.7,
      "110": 27.5,
      "376": 27.4,
      "76": 27.3,
      "173": 27,
      "351": 26.9,
      "176": 26.9,
      "116": 26.9,
      "168": 26.7,
      "75": 26.5,
      "245": 26.4,
      "125": 26.4,
      "123": 26.3,
      "115": 26.3,
      "277": 26.1,
      "97": 26.1,
      "177": 26,
      "44": 26,
      "117": 25.9,
      "179": 25.5,
      "383": 25.2,
      "280": 25.2,
      "113": 25,
      "103": 25,
      "91": 24.9,
      "55": 24.9,
      "50": 24.9,
      "281": 24.8,
      "104": 24.8,
      "174": 24.7,
      "169": 24.7,
      "109": 24.7,
      "52": 24.5,
      "342": 24.4,
      "355": 24.3,
      "246": 24.3,
      "362": 24.1,
      "53": 24,
      "48": 23.8,
      "203": 23.7,
      "195": 23.7,
      "112": 23.6,
      "92": 23.6,
      "118": 23.5,
      "98": 23.5,
      "51": 23.4,
      "194": 23.3,
      "63": 23.3,
      "328": 23.2,
      "154": 23.2,
      "372": 23.1,
      "343": 23.1,
      "105": 23.1,
      "371": 23,
      "186": 22.7,
      "381": 22.6,
      "124": 22.6,
      "364": 22.4,
      "71": 22,
      "344": 21.9,
      "114": 21.9,
      "348": 21.8,
      "100": 21.8,
      "74": 21.8,
      "198": 21.7,
      "205": 21.6,
      "82": 21.6,
      "320": 21.4,
      "374": 21.3,
      "193": 21.2,
      "388": 21,
      "111": 21,
      "201": 20.8,
      "375": 20.7,
      "358": 20.7,
      "94": 20.7,
      "365": 20.6,
      "349": 20.5,
      "19": 20.5,
      "247": 20.4,
      "119": 20.4,
      "96": 20.4,
      "380": 20.3,
      "73": 20.1,
      "345": 19.8,
      "368": 19.7,
      "200": 19.3,
      "182": 19.3,
      "197": 19.2,
      "338": 19,
      "164": 19,
      "346": 18.9,
      "330": 18.7,
      "218": 18.6,
      "62": 18.6,
      "340": 18.5,
      "95": 18.3,
      "120": 18.2,
      "59": 18.1,
      "181": 18,
      "223": 17.9,
      "224": 17.9,
      "357": 17.8,
      "212": 17.8,
      "359": 17.6,
      "324": 17.6,
      "188": 17.6,
      "248": 17.4,
      "196": 17.4,
      "373": 17.3,
      "356": 17.3,
      "99": 17.2,
      "138": 17.1,
      "60": 16.9,
      "370": 16.6,
      "219": 16.6,
      "352": 16.3,
      "220": 16.3,
      "180": 16.3,
      "347": 16.2,
      "185": 16.2,
      "208": 15.9,
      "222": 15.9,
      "184": 15.7,
      "183": 15.7,
      "379": 15.6,
      "175": 15.5,
      "249": 15.4,
      "207": 15.4,
      "129": 15.2,
      "282": 15.1,
      "214": 15.1,
      "228": 15.1,
      "187": 15.1,
      "131": 14.9,
      "353": 14.7,
      "253": 14.5,
      "231": 14.5,
      "190": 14.5,
      "250": 14.4,
      "130": 14.4,
      "310": 14.3,
      "206": 14.3,
      "387": 14.2,
      "221": 14.2,
      "233": 14.1,
      "318": 13.9,
      "211": 13.9,
      "132": 13.8,
      "251": 13.7,
      "275": 13.7,
      "335": 13.6,
      "209": 13.6,
      "133": 13.6,
      "229": 13.4,
      "341": 13.3,
      "322": 13.3,
      "226": 13.3,
      "312": 13.1,
      "213": 13.1,
      "210": 13,
      "259": 12.5,
      "216": 12.3,
      "232": 12.3,
      "311": 12.2,
      "227": 12.1,
      "363": 12,
      "258": 12,
      "296": 11.9,
      "290": 11.7,
      "156": 11.6,
      "314": 11.5,
      "263": 11.5,
      "189": 11.5,
      "332": 11.4,
      "225": 11.4,
      "285": 11.3,
      "369": 11.2,
      "329": 11.2,
      "261": 11.2,
      "202": 11.2,
      "331": 11,
      "315": 11,
      "313": 10.9,
      "256": 10.8,
      "321": 10.7,
      "254": 10.7,
      "389": 10.4,
      "377": 10.4,
      "69": 10.4,
      "289": 10.3,
      "284": 10.3,
      "262": 10.3,
      "215": 10.3,
      "241": 10.2,
      "384": 10.1,
      "236": 10.1,
      "204": 10.1,
      "378": 10,
      "255": 10,
      "316": 9.9,
      "317": 9.8,
      "299": 9.8,
      "295": 9.8,
      "283": 9.7,
      "238": 9.7,
      "257": 9.7,
      "252": 9.7,
      "391": 9.6,
      "390": 9.6,
      "304": 9.6,
      "230": 9.6,
      "298": 9.5,
      "260": 9.4,
      "306": 9.3,
      "287": 9.3,
      "240": 9.3,
      "367": 9.2,
      "237": 9.1,
      "191": 9.1,
      "288": 9,
      "297": 8.9,
      "291": 8.9,
      "286": 8.9,
      "217": 8.9,
      "303": 8.8,
      "239": 8.8,
      "382": 8.7,
      "301": 8.6,
      "333": 8.2,
      "84": 8.2,
      "309": 8.1,
      "302": 8.1,
      "292": 8,
      "326": 7.9,
      "305": 7.9,
      "393": 7.8,
      "360": 7.8,
      "300": 7.7,
      "264": 7.7,
      "276": 7.7,
      "392": 7.4,
      "395": 7.3,
      "337": 7.2,
      "293": 7,
      "307": 6.9,
      "394": 6.8,
      "397": 6.7,
      "308": 6.7,
      "399": 6.5,
      "334": 6.5,
      "398": 6.4,
      "396": 6.4,
      "319": 6.4,
      "403": 6.2,
      "323": 6.1,
      "401": 5.9,
      "294": 5.9,
      "235": 5.6,
      "400": 5.1,
      "361": 5.1,
      "402": 4.3,
      "385": 4.3,
      "327": 4.2,
      "325": 4.1,
      "336": 3.8,
      "366": 3.7,
      "386": 3.4,
      "339": 2.9,
      "354": 2.7
    },
    "440": {
      "TF_SCOUT_LONG_DISTANCE_RUNNER": 55.6,
      "TF_HEAVY_DAMAGE_TAKEN": 46.2,
      "TF_GET_CONSECUTIVEKILLS_NODEATHS": 42.9,
      "TF_PYRO_CAMP_POSITION": 35.2,
      "TF_KILL_NEMESIS": 32.9,
      "TF_BURN_PLAYERSINMINIMUMTIME": 32.4,
      "TF_PYRO_BURN_MEDICPAIR": 31.8,
      "TF_SNIPER_KILL_MIDAIR_SCOUT": 30.9,
      "TF_HEAVY_KILL_MIDAIR_MINIGUN": 30.3,
      "TF_DEMOMAN_BOUNCE_AND_KILL": 30.2,
      "TF_PYRO_KILL_TEAMWORK": 30,
      "TF_PYRO_DOUBLE_KO": 29.8,
      "TF_ENGINEER_DISPENSER_HEAL_GROUP": 29.6,
      "TF_HEAVY_TAKE_MULTI_DAMAGE": 29.3,
      "TF_HALLOWEEN_DOMINATE_FOR_HAT": 28.8,
      "TF_SNIPER_RIFLE_NO_MISSING": 28.3,
      "TF_SNIPER_HEADSHOT_DEMOMAN": 28.1,
      "TF_SPY_BUMP_CLOAKED_SPY": 27.1,
      "TF_ENGINEER_FREEZECAM_SENTRY": 26.7,
      "TF_GENERAL_KILL_ENEMIES_AFTER_TELEPORTING": 26.5,
      "TF_SNIPER_ACHIEVE_PROGRESS1": 26.2,
      "TF_SNIPER_KILL_WEAPONS": 26.1,
      "TF_GET_HEALED_BYENEMY": 25.7,
      "TF_FIRE_WATERJUMP": 25,
      "TF_PYRO_SIMULBURN_SCOUTS": 24.9,
      "TF_ENGINEER_HELP_BUILD_STRUCTURE": 24.6,
      "TF_ENGINEER_SENTRY_AVENGES_YOU": 24.4,
      "TF_SOLDIER_DEFEND_MEDIC": 24.2,
      "TF_DOMINATE_FOR_GOGGLES": 23.9,
      "TF_WIN_MULTIPLEGAMES": 23.7,
      "TF_ENGINEER_ACHIEVE_PROGRESS1": 23.1,
      "TF_SNIPER_KILL_INVIS_SPY": 23.1,
      "TF_GET_HEADSHOTS": 23,
      "TF_SOLDIER_CROUCH_ROCKET_JUMP": 22.7,
      "TF_SPY_SURVIVE_BURNING": 22.5,
      "TF_SPY_ACHIEVE_PROGRESS1": 22.3,
      "TF_WIN_2FORT_NOENEMYCAPS": 22.3,
      "TF_SPY_BACKSTAB_QUICK_KILLS": 22.2,
      "TF_SNIPER_DOMINATE_SNIPER": 21.9,
      "TF_SOLDIER_KILL_AIRBORNE_TARGET_WHILE_AIRBORNE": 21.8,
      "TF_MEDIC_SETUP_CHARGE": 21.8,
      "TF_SNIPER_HEADSHOT_SNIPERS": 21.7,
      "TF_MEDIC_SWITCH_TO_MEDIC": 21.3,
      "TF_SPY_BACKSTAB_DISGUISE_TARGET": 20.9,
      "TF_SNIPER_KILL_AT_ROUNDSTART": 20.9,
      "TF_MVM_KILL_BOMB_CARRIERS": 20.7,
      "TF_HEAVY_FIRST_TO_CAP": 20.7,
      "TF_HEAVY_SURVIVE_CROCKET": 20.7,
      "TF_MEDIC_HEAL_ACHIEVER": 20.6,
      "TF_SNIPER_BOW_KILL_WHILEDEAD": 20.5,
      "TF_SOLDIER_KILL_SPY_KILLER": 20.4,
      "TF_SPY_REVENGE_WITH_BACKSTAB": 20.4,
      "TF_SNIPER_DESTROY_SENTRYGUNS": 20.4,
      "TF_PYRO_BURN_RJ_SOLDIER": 20.4,
      "TF_SNIPER_ACHIEVE_PROGRESS2": 20.2,
      "TF_PYRO_BURN_SPIES_AS_YOU": 20.2,
      "TF_ENGINEER_KILL_ASSIST": 20,
      "TF_ENGINEER_MOVE_SENTRY_GET_KILL": 20,
      "TF_SOLDIER_ACHIEVE_PROGRESS1": 19.9,
      "TF_SPY_BACKSTAB_ENEMY_SWITCH_PYRO": 19.9,
      "TF_SCOUT_SURVIVE_DAMAGE": 19.9,
      "TF_PYRO_REVEAL_SPIES": 19.8,
      "TF_ENGINEER_SHOTGUN_KILL_PREV_SENTRY_TARGET": 19.7,
      "TF_PYRO_ACHIEVE_PROGRESS1": 19.5,
      "TF_MEDIC_HEAL_UNDER_FIRE": 19.5,
      "TF_SOLDIER_SHOOT_MULT_CRITS": 19.4,
      "TF_SPY_KILL_SPY_WITH_KNIFE": 19.4,
      "TF_MEDIC_HEAL_ENGINEER": 19.4,
      "TF_MVM_EARN_MONEY_BONUS": 18.9,
      "TF_ENGINEER_REPAIR_SENTRY_W_MEDIC": 18.9,
      "TF_SCOUT_CAPTURE_LAST_POINT": 18.9,
      "TF_SPY_KILL_WORKING_ENGY": 18.7,
      "TF_SCOUT_CAP_FLAG_WITHOUT_ATTACKING": 18.7,
      "TF_HEAVY_EARN_MEDIC_DOMINATION": 18.6,
      "TF_SNIPER_KILL_CHARGED_MEDIC": 18.4,
      "TF_HEAVY_KILL_CRIT_PUNCH": 18.4,
      "TF_PYRO_DOMINATE_LEAVESVR": 18.3,
      "TF_GET_TURRETKILLS": 18.3,
      "TF_HEAVY_KILL_WHILE_SPUNUP": 18.1,
      "TF_SPY_ACHIEVE_PROGRESS2": 17.9,
      "TF_PYRO_BURN_MEDICS_CHARGED": 17.7,
      "TF_SOLDIER_KILL_PYRO": 17.6,
      "TF_GET_MULTIPLEKILLS": 17.6,
      "TF_MVM_PICKUP_MONEY_ABOUT_TO_EXPIRE": 17.5,
      "TF_SPY_BACKSTAB_DISGUISED_SPY": 17.4,
      "TF_SNIPER_KILL_UNSCOPED": 17.4,
      "TF_MEDIC_RAPID_CHARGE": 17.4,
      "TF_SPY_BACKSTAB_DOMINATING_ENEMY": 17.2,
      "TF_ENGINEER_ACHIEVE_PROGRESS2": 17.1,
      "TF_MEDIC_COUNTER_CHARGE": 17.1,
      "TF_DEMOMAN_ACHIEVE_PROGRESS1": 17,
      "TF_PYRO_KILL_POSTDEATH": 17,
      "TF_HEAVY_ACHIEVE_PROGRESS1": 16.9,
      "TF_ENGINEER_KILL_DISGUISED_SPY": 16.8,
      "TF_GET_HEALPOINTS": 16.8,
      "TF_SNIPER_KILL_RJER": 16.6,
      "TF_SOLDIER_DUO_SOLDIER_KILLS": 16.5,
      "TF_SNIPER_ACHIEVE_PROGRESS3": 16.5,
      "TF_PYRO_ACHIEVE_PROGRESS2": 16.5,
      "TF_COMPLETE_TRAINING": 16.4,
      "TF_SOLDIER_ACHIEVE_PROGRESS2": 16.3,
      "TF_HALLOWEEN_DISGUISED_SPY_KILL": 16.2,
      "TF_SOLDIER_KILL_ENGY": 16,
      "TF_HEAVY_KILL_SHOTGUN": 16,
      "TF_SNIPER_BOW_PINCUSHION": 15.9,
      "TF_MEDIC_INVITE_JOIN_CHARGE": 15.9,
      "TF_SPY_BACKSTAB_MEDIC_CHARGED": 15.8,
      "TF_DEMOMAN_KILL_BUILDING_DIRECT_HIT": 15.7,
      "TF_CHRISTMAS_COLLECT_GIFTS": 15.5,
      "TF_SCOUT_KILL_CHARGED_MEDICS": 15.5,
      "TF_SPY_ACHIEVE_PROGRESS3": 15.4,
      "TF_MEDIC_ACHIEVE_PROGRESS1": 15.3,
      "TF_PLAY_GAME_EVERYCLASS": 15.3,
      "TF_MVM_KILL_SENTRY_BUSTER": 15.2,
      "TF_SOLDIER_KILL_SNIPER_WHILE_DEAD": 15.2,
      "TF_SPY_DOMINATE_SNIPER": 15.2,
      "TF_SCOUT_ACHIEVE_PROGRESS1": 15.2,
      "TF_MVM_COMPLETE_POP_FILE": 15.1,
      "TF_PYRO_BURN_SNIPERS_ZOOMED": 15.1,
      "TF_PYRO_KILL_FROM_BEHIND": 15,
      "TF_SPY_BREAK_SHIELD_KILL_SNIPER": 14.8,
      "TF_SPY_SAP_BUILDING_BACKSTAB_ENGY": 14.8,
      "TF_HEAVY_TELEPORT_FAST_KILL": 14.8,
      "TF_MULTIPLE_BFF": 14.6,
      "TF_DEMOMAN_ACHIEVE_PROGRESS2": 14.6,
      "TF_PYRO_ACHIEVE_PROGRESS3": 14.6,
      "TF_SCOUT_FAST_CAP": 14.5,
      "TF_SCOUT_DESTROY_BUILDINGS_BEING_BUILT": 14.5,
      "TF_SCOUT_DOUBLE_JUMPS": 14.4,
      "TF_HEAVY_FIRE_LOTS": 14.4,
      "TF_MVM_COMPLETE_WAVE_WITHOUT_DYING": 14.3,
      "TF_SPY_FEIGN_DEATH_KILL": 14.3,
      "TF_SPY_BACKSTAB_SNIPERS": 14.3,
      "TF_SCOUT_START_AND_FINISH_CAP": 14.3,
      "TF_HEAVY_ACHIEVE_PROGRESS2": 14.3,
      "TF_PYRO_KILL_AXE_SMALL": 14.3,
      "TF_DEMOMAN_CRIT_SWORD_KILL": 14.2,
      "TF_WIN_DUSTBOWL_NOENEMYCAPS": 14.2,
      "TF_ENGINEER_REMOVE_SAPPER_LONG_DIST": 14.1,
      "TF_DEMOMAN_DECAPITATE_CLOAKED_SPY": 14.1,
      "TF_ENGINEER_ACHIEVE_PROGRESS3": 14,
      "TF_ENGINEER_REVENGE_CRIT_SENTRY_KILLER": 14,
      "TF_SOLDIER_ACHIEVE_PROGRESS3": 14,
      "TF_SPY_BACKSTAB_MEDIC_HEALING_YOU": 14,
      "TF_SCOUT_THREE_FLAGCAPS": 14,
      "TF_PYRO_REFLECT_CROCKET_KILL": 14,
      "TF_WIN_WELL_MINIMUMTIME": 14,
      "TF_REPLAY_SAVE_REPLAY": 13.9,
      "TF_DEMOMAN_DUO_DEMOMAN_KILLS": 13.9,
      "TF_DEMOMAN_KILL_X_WITH_DIRECTPIPE": 13.9,
      "TF_SOLDIER_BOUNCE_THEN_SHOTGUN": 13.9,
      "TF_SOLDIER_KILL_TWENTY_FROM_ABOVE": 13.9,
      "TF_SNIPER_JARATE_EXTINGUISH": 13.9,
      "TF_SCOUT_DESTROY_SENTRY_WITH_PISTOL": 13.9,
      "TF_ENGINEER_KILL_SPY_TWO_SAPPERS": 13.8,
      "TF_SPY_BACKSTAB_MEDIC_PAIR": 13.8,
      "TF_SNIPER_CAPTURE_FLAG": 13.8,
      "TF_HEAVY_UNCOVER_SPIES": 13.8,
      "TF_HEAVY_KILL_DOMINATED": 13.8,
      "TF_MEDIC_KILL_HEALED_SPY": 13.8,
      "TF_KILL_CHARGING_DEMO": 13.7,
      "TF_SOLDIER_DESTROY_SENTRY_OUT_OF_RANGE": 13.7,
      "TF_PYRO_KILL_TAUNT": 13.7,
      "TF_PYRO_FORCE_WATERJUMP": 13.7,
      "TF_HEAVY_ASSIST_HEAVY_GRIND": 13.6,
      "TF_DEMOMAN_CHARGE_KILL": 13.5,
      "TF_HEAVY_REVENGE_ASSIST": 13.5,
      "TF_HALLOWEEN_BOSS_KILL": 13.4,
      "TF_SPY_KNIFE_KILL_WHILE_JARATED": 13.4,
      "TF_SCOUT_ACHIEVE_PROGRESS2": 13.4,
      "TF_SOLDIER_KILL_AIRBORNE_WITH_DIRECT_HIT": 13.3,
      "TF_HALLOWEEN_KILL_SCARED_PLAYER": 13.3,
      "TF_PYRO_KILL_GRIND": 13.3,
      "TF_DEMOMAN_DECAPITATE_NEMESIS": 13.2,
      "TF_SNIPER_JARATE_REVEAL_SPY": 13.2,
      "TF_SCOUT_DESTROY_TELEPORTERS": 13.2,
      "TF_PYRO_KILL_CARRIERS": 13.2,
      "TF_MEDIC_ACHIEVE_PROGRESS2": 13.2,
      "TF_DEMOMAN_ENVIRONMENTAL_KILL": 13.1,
      "TF_DEMOMAN_ACHIEVE_PROGRESS3": 13.1,
      "TF_SOLDIER_KILL_ON_FIRE": 13.1,
      "TF_SCOUT_CAPTURE_THREE_POINTS": 13.1,
      "TF_PYRO_CAMP_TELEPORTERS": 13.1,
      "TF_TEAM_PYROVISION": 13,
      "TF_SNIPER_FREEZECAM_WAVE": 13,
      "TF_SCOUT_KNOCK_INTO_TRAIN": 13,
      "TF_SNIPER_KILL_SPIES_MELEE": 12.9,
      "TF_HEAVY_CLEAR_STICKYBOMBS": 12.9,
      "TF_HEAVY_KILL_TAUNT": 12.9,
      "TF_PYRO_KILL_UBERCHARGE": 12.9,
      "TF_ENGINEER_BUILDING_CARRY": 12.8,
      "TF_DEMOMAN_DECAPITATE_PLAYERS": 12.8,
      "TF_SNIPER_BOW_PIN_HEAVY": 12.8,
      "TF_SNIPER_JARATE_DOMINATED": 12.8,
      "TF_PYRO_IGNITE_FLAREGUN": 12.8,
      "TF_DEMOMAN_STICKJUMP_DISTANCE": 12.7,
      "TF_SPY_CAMP_POSITION": 12.7,
      "TF_HEAVY_ACHIEVE_PROGRESS3": 12.7,
      "TF_ENGINEER_TANK_DAMAGE": 12.6,
      "TF_SPY_SAPPER_TEAMWORK": 12.6,
      "TF_SNIPER_TAUNT_KILL": 12.6,
      "TF_SNIPER_JARATE_MEDIC_PAIR": 12.6,
      "TF_DEMOMAN_KILL_X_SCOUTS_PYROS": 12.5,
      "TF_SOLDIER_KILL_GROUP_WITH_CROCKET": 12.5,
      "TF_SPY_MEDIC_HEALING_KILL_ENEMY": 12.5,
      "TF_SPY_TAUNT_KILL": 12.5,
      "TF_SCOUT_KILL_IN_DODGE_COOLDOWN": 12.5,
      "TF_DEMOMAN_DECAPITATE_PLAYERS_FAST": 12.4,
      "TF_SOLDIER_RJ_EQUALIZER_KILL": 12.4,
      "TF_SOLDIER_KILL_DEFENSELESS": 12.4,
      "TF_HALLOWEEN_COLLECT_PUMPKINS": 12.4,
      "TF_SCOUT_CARRIER_KILL_CARRIER": 12.4,
      "TF_MEDIC_BONESAW_NOMISSES": 12.4,
      "TF_MAPS_DOOMSDAY_DEFEND_CARRIER": 12.3,
      "TF_ENGINEER_TELEPORT_GRIND": 12.2,
      "TF_SNIPER_HEADSHOT_POST_INVULN": 12.2,
      "TF_SCOUT_ACHIEVE_PROGRESS3": 12.2,
      "TF_MEDIC_ASSIST_HEAVY_LONG": 12.2,
      "TF_HALLOWEEN_COLLECT_GOODY_BAG": 12.1,
      "TF_SOLDIER_RIDE_THE_CART": 12.1,
      "TF_MEDIC_ACHIEVE_PROGRESS3": 12.1,
      "TF_MEDIC_CHARGE_BLOCKER": 12.1,
      "TF_MVM_ENGINEER_ESCAPE_SENTRY_BUSTER": 12,
      "TF_SNIPER_KILL_FAILED_SPY": 12,
      "TF_SNIPER_GET_BACKSTABBED": 12,
      "TF_PYRO_KILL_AXE_LARGE": 12,
      "TF_PYRO_KILL_SPIES": 12,
      "TF_MEDIC_KILL_WHILE_CHARGED": 12,
      "TF_MEDIC_TOP_SCOREBOARD": 12,
      "TF_SPY_FAST_CAP": 11.9,
      "TF_SNIPER_FREEZECAM_HAT": 11.9,
      "TF_DEMOMAN_TAUNT_KILL": 11.8,
      "TF_SCOUT_STEAL_SANDWICH": 11.8,
      "TF_HALLOWEEN_EYEBOSS_KILL": 11.7,
      "TF_HEAVY_ASSIST_MEDIC_LARGE": 11.7,
      "TF_PYRO_FREEZECAM_TAUNTS": 11.7,
      "TF_MEDIC_HEAL_CALLERS": 11.7,
      "TF_SOLDIER_KILL_TAUNT": 11.6,
      "TF_PYRO_KILL_TAUNTERS": 11.6,
      "TF_WIN_GRAVELPIT_NOENEMYCAPS": 11.6,
      "TF_SOLDIER_THREE_DOMINATIONS": 11.5,
      "TF_SNIPER_JARATE_GROUP": 11.5,
      "TF_PYRO_DESTROY_BUILDINGS": 11.5,
      "TF_SOLDIER_KILL_TWO_DURING_ROCKET_JUMP": 11.4,
      "TF_SCOUT_DODGE_DAMAGE": 11.4,
      "TF_PYRO_REFLECT_PROJECTILES": 11.4,
      "TF_MEDIC_EXTINGUISH_TEAMMATES": 11.3,
      "TF_WIN_HYDRO_NOENEMYCAPS": 11.3,
      "TF_ENGINEER_REVENGE_CRIT_LIFE": 11.2,
      "TF_SNIPER_BOW_KILL_FLAGCARRIER": 11.2,
      "TF_HEAVY_STAND_NEAR_DISPENSER": 11.2,
      "TF_ENGINEER_DISPENSER_EXTINGUISH": 11.1,
      "TF_DEMOMAN_KILL3_WITH_DETONATION": 11.1,
      "TF_SNIPER_KILL_OBJECTIVES": 11.1,
      "TF_PYRO_DEFEND_POINTS": 11.1,
      "TF_MEDIC_ASSIST_MEDIC": 11.1,
      "TF_DEMOMAN_FREEZECAM_SMILE": 11,
      "TF_PYRO_KILL_GRIND_LARGE": 11,
      "TF_MEDIC_SIMUL_CHARGE": 11,
      "TF_MAPS_DOOMSDAY_PUSH_BACK_AND_WIN": 10.9,
      "TF_HALLOWEEN_BOSS_KILL_MELEE": 10.8,
      "TF_SCOUT_MAX_STUNS": 10.8,
      "TF_SCOUT_FLAG_CAP_GRIND": 10.8,
      "TF_HEAVY_RECEIVE_UBER_GRIND": 10.8,
      "TF_MEDIC_BONESAW_SPY_CALLERS": 10.8,
      "TF_ENGINEER_TAUNT_KILL": 10.7,
      "TF_DEMOMAN_DESTROY_BUILDINGS_GRIND": 10.7,
      "TF_SCOUT_TAUNT_KILL": 10.7,
      "TF_SCOUT_DOUBLEJUMP_KILL": 10.7,
      "TF_SCOUT_IRON_MAN_KILLS": 10.7,
      "TF_MEDIC_ASSIST_PYRO": 10.7,
      "TF_MEDIC_SAVE_TEAMMATE": 10.7,
      "TF_HALLOWEEN_MERASMUS_KILL": 10.6,
      "TF_MVM_MAX_PLAYER_RESISTANCES": 10.6,
      "TF_MVM_MAX_PRIMARY_UPGRADES": 10.6,
      "TF_MAPS_FOUNDRY_WIN_MINTIME": 10.6,
      "TF_REPLAY_EDIT_TIME": 10.6,
      "TF_ENGINEER_UPGRADE_BUILDINGS": 10.6,
      "TF_DEMOMAN_KILL_PLAYER_AFTER_TP": 10.6,
      "TF_DEMOMAN_DECAPITATE_EQUALIZER": 10.6,
      "TF_HALLOWEEN_LOOT_ISLAND": 10.5,
      "TF_SOLDIER_NEMESIS_SHOVEL_KILL": 10.5,
      "TF_SPY_AMBASSADOR_SCOUT_GRIND": 10.5,
      "TF_SPY_AMBASSADOR_GRIND": 10.5,
      "TF_HEAVY_KILL_MEDIC_PAIR": 10.5,
      "TF_MAPS_DOOMSDAY_SOLO_CAPTURE": 10.4,
      "TF_SPY_BACKSTAB_ENGY_SAP_BUILDING": 10.4,
      "TF_SNIPER_KILL_GRIND": 10.4,
      "TF_HEAVY_HEAL_MEDIKITS": 10.4,
      "TF_MEDIC_SAVE_FALLING_TEAMMATE": 10.4,
      "TF_DEMOMAN_KILL_X_DEFENDING": 10.3,
      "TF_HALLOWEEN_PUMPKIN_KILL": 10.3,
      "TF_HEAVY_KILL_CAPPING_ENEMIES": 10.3,
      "TF_MEDIC_FREEZECAM_RAGDOLL": 10.3,
      "TF_MVM_DESTROY_TANK_WHILE_DEPLOYING": 10.2,
      "TF_ENGINEER_SENTRY_KILL_CAPS": 10.2,
      "TF_DEMOMAN_DOMINATE_THREE_ENGINEERS": 10.2,
      "TF_SPY_BACKSTAB_FRIENDS": 10.2,
      "TF_MEDIC_CHARGE_JUGGLE": 10.2,
      "TF_MEDIC_ASSIST_CAPTURER": 10.2,
      "TF_MVM_DESTROY_TANK_QUICKLY": 10.1,
      "TF_REPLAY_PERFORMANCE_MODE": 10.1,
      "TF_SCOUT_FIRST_BLOOD": 10.1,
      "TF_HALLOWEEN_MERASMUS_COLLECT_LOOT": 10,
      "TF_MAPS_FOUNDRY_ACHIEVE_PROGRESS1": 10,
      "TF_SOLDIER_EQUALIZER_STREAK": 10,
      "TF_SCOUT_STUN_SCOUT_WITH_THEIR_BALL": 10,
      "TF_SCOUT_STUN_UBER_ENEMIES": 10,
      "TF_DEMOMAN_KILL_PLAYER_YOU_DIDNT_SEE": 9.9,
      "TF_HALLOWEEN_HELLTOWER_RARE_SPELL": 9.9,
      "TF_MAPS_FOUNDRY_KILL_CAPPING_ENEMY": 9.9,
      "TF_ENGINEER_FREEZECAM_TAUNT": 9.9,
      "TF_DEMOMAN_KILL_ENGI_SENTRY_DISPENSER": 9.9,
      "TF_SOLDIER_FREEZECAM_TAUNT": 9.9,
      "TF_SOLDIER_DEFEND_CAP_THIRTY_TIMES": 9.9,
      "TF_SPY_KILL_CP_DEFENDERS": 9.9,
      "TF_SCOUT_KILL_FROM_BEHIND": 9.9,
      "TF_HEAVY_PAYLOAD_CAP_GRIND": 9.9,
      "TF_PYRO_KILL_MULTIWEAPONS": 9.9,
      "TF_MEDIC_BONESAW_MEDICS": 9.9,
      "TF_MVM_NO_ALARMS_IN_FINAL_WAVE": 9.8,
      "TF_DEMOMAN_KILL_X_HEAVIES_FULLHP_ONEDET": 9.8,
      "TF_MAPS_DOOMSDAY_ACHIEVE_PROGRESS1": 9.7,
      "TF_DEMOMAN_KILL_TWO_DURING_STICKYJUMP": 9.7,
      "TF_SOLDIER_ASSIST_MEDIC_UBER": 9.7,
      "TF_SOLDIER_BUFF_TEAMMATES": 9.7,
      "TF_HEAVY_EAT_SANDWICHES": 9.7,
      "TF_PLAY_GAME_EVERYMAP": 9.7,
      "TF_MVM_USE_CRIT_BOTTLE": 9.6,
      "TF_ENGINEER_DESTROY_SAPPERS": 9.6,
      "TF_SOLDIER_KILL_FIVE_STUNNED": 9.6,
      "TF_SNIPER_JARATE_ASSISTS": 9.6,
      "TF_HEAVY_DEFEND_CONTROL_POINT": 9.6,
      "TF_SOLDIER_GIB_GRIND": 9.5,
      "TF_PLAY_GAME_FRIENDSONLY": 9.5,
      "TF_MAPS_FOUNDRY_PUSH_BACK_AND_WIN": 9.4,
      "TF_ENGINEER_MANUAL_SENTRY_KILLS_BEYOND_RANGE": 9.4,
      "TF_DEMOMAN_KILL3_WITH_PIPE_SETUPS": 9.4,
      "TF_SCOUT_STUN_INTO_TRAIN": 9.4,
      "TF_PYRO_BURN_SPY_TAUNT": 9.4,
      "TF_HALLOWEEN_HELLTOWER_SKULL_ISLAND_REWARD": 9.3,
      "TF_DEMOMAN_STICKYJUMP_CAP": 9.3,
      "TF_PYRO_KILL_HEAVIES": 9.3,
      "TF_MEDIC_ASSIST_VS_NEMESES": 9.3,
      "TF_ENGINEER_MANUAL_SENTRY_ABSORB_DMG": 9.2,
      "TF_DEMOMAN_FREEZECAM_RUMP": 9.2,
      "TF_DEMOMAN_MELEE_KILL_WHILE_STICKYJUMPING": 9.2,
      "TF_MEDIC_ASSIST_SOLDIER": 9.2,
      "TF_MEDIC_ASSIST_HEAVY": 9.2,
      "TF_MVM_ROCKET_SPECIALIST_STUN_GRIND": 9.1,
      "TF_ENGINEER_HEAVY_ASSIST": 9.1,
      "TF_ENGINEER_WASTE_METAL_GRIND": 9.1,
      "TF_SOLDIER_MVP": 9.1,
      "TF_SOLDIER_FREEZECAM_GIBS": 9.1,
      "TF_SPY_FREEZECAM_FLICK": 9.1,
      "TF_SNIPER_BOW_KILL_MEDIC_PAIR": 9.1,
      "TF_MAPS_DOOMSDAY_DENY_NEUTRAL_PICKUP": 9,
      "TF_SNIPER_JARATE_KILL_MELEE": 9,
      "TF_SCOUT_ASSIST_MEDIC": 9,
      "TF_MEDIC_ASSIST_SCOUT": 9,
      "TF_MVM_SOLDIER_BUFF_TEAM": 8.9,
      "TF_MVM_USE_AMMO_BOTTLE": 8.9,
      "TF_MAPS_FOUNDRY_BACK_AND_FORTH_BATTLE": 8.9,
      "TF_REPLAY_BROWSE_REPLAYS": 8.9,
      "TF_SOLDIER_DESTROY_STICKIES": 8.9,
      "TF_SCOUT_WELL_EARLY_KILL": 8.9,
      "TF_PYRO_KILL_UNDERWATER": 8.9,
      "TF_MEDIC_HEAL_LARGE": 8.9,
      "TF_MEDIC_SYRINGE_SCOUTS": 8.9,
      "TF_DEMOMAN_AIR_BURST_KILLS": 8.8,
      "TF_SPY_BACKSTAB_CAPPING_ENEMIES": 8.8,
      "TF_SPY_BACKSTAB_GRIND": 8.8,
      "TF_SNIPER_TOP_SCOREBOARD_GRIND": 8.8,
      "TF_HEAVY_DEFEND_MEDIC": 8.8,
      "TF_MVM_DESTROY_TWO_TANKS": 8.7,
      "TF_MAPS_DOOMSDAY_RIDE_THE_ELEVATOR": 8.7,
      "TF_SCOUT_KILL_STUNNED": 8.7,
      "TF_HEAVY_FREEZECAM_TAUNT": 8.7,
      "TF_HEAVY_BLOCK_CART": 8.7,
      "TF_MVM_USE_UBER_BOTTLE": 8.6,
      "TF_HALLOWEEN_CRAFT_SAXTON_MASK": 8.6,
      "TF_DEMOMAN_DESTROY_BUILDINGS_WITH_MEDIC": 8.6,
      "TF_SCOUT_LIFETIME_KILLS": 8.6,
      "TF_HEAVY_KILL_SCOUTS": 8.6,
      "TF_HEAVY_BLOCK_INVULN_HEAVY": 8.6,
      "TF_MAPS_FOUNDRY_PUSH_INTO_CAULDRON": 8.5,
      "TF_MAPS_FOUNDRY_TELEPORT_AND_CAP": 8.5,
      "TF_REPLAY_YOUTUBE_VIEWS_TIER2": 8.5,
      "TF_REPLAY_YOUTUBE_VIEWS_TIER1": 8.5,
      "TF_SPY_AMBASSADOR_SNIPER_GRIND": 8.5,
      "TF_SCOUT_BLOCK_CAPS": 8.5,
      "TF_MEDIC_CHARGE_FRIENDS": 8.5,
      "TF_MEDIC_ASSIST_DEMOMAN": 8.5,
      "TF_MAPS_FOUNDRY_KILL_ENEMY_ON_ROOF": 8.4,
      "TF_MAPS_FOUNDRY_PLAY_EACH_CLASS": 8.4,
      "TF_MAPS_FOUNDRY_FAST_FINAL_CAP": 8.4,
      "TF_ENGINEER_HELP_MANUAL_SENTRY": 8.4,
      "TF_ENGINEER_MANUAL_CLOAKED_SPY_KILL": 8.4,
      "TF_SOLDIER_BUFF_FRIENDS": 8.4,
      "TF_MAPS_DOOMSDAY_KILL_ENEMIES_ON_ELEVATOR": 8.3,
      "TF_MAPS_FOUNDRY_PLAY_GAME_FRIENDS": 8.3,
      "TF_ENGINEER_KILL_FLAG_CARRIERS": 8.3,
      "TF_HEAVY_KILL_HEAVIES_GLOVES": 8.3,
      "TF_MVM_SNIPER_KILL_GROUP": 8.2,
      "TF_MAPS_DOOMSDAY_PUSH_INTO_EXHAUST": 8.2,
      "TF_ENGINEER_KILL_SENTRY_WITH_SENTRY": 8.2,
      "TF_HEAVY_KILL_FLAG_CARRIERS": 8.2,
      "TF_ENGINEER_DISPENSER_HEAL_GRIND": 8.1,
      "TF_ENGINEER_KILL_SNIPERS_SENTRY": 8.1,
      "TF_SOLDIER_KILL_WITH_EQUALIZER_WHILE_HURT": 8.1,
      "TF_SOLDIER_KILL_DEMOMAN_GRIND": 8.1,
      "TF_SCOUT_FIRST_BLOOD_KILL": 8.1,
      "TF_TAUNT_CONGA_LINE": 8,
      "TF_MAPS_DOOMSDAY_KILL_CARRIERS": 8,
      "TF_DEMOMAN_KILL_X_CAPPING_ONEDET": 8,
      "TF_DEMOMAN_KILL_SOLDIER_GRIND": 8,
      "TF_SCOUT_STUN_CAPPING_ENEMIES": 8,
      "TF_MAPS_DOOMSDAY_PLAY_GAME_FRIENDS": 7.9,
      "TF_DEMOMAN_KILLXSAPPINGSPIES": 7.9,
      "TF_MEDIC_HEAL_HUGE": 7.9,
      "TF_SPY_SAPPER_GRIND": 7.8,
      "TF_HEAVY_ASSIST_GRIND": 7.8,
      "TF_MVM_COMPLETE_TOUR": 7.7,
      "TF_DEMOMAN_DESTROY_X_STICKYBOMBS": 7.6,
      "TF_HEAVY_KILL_UNDERWATER": 7.6,
      "TF_MEDIC_HEAL_GRIND": 7.6,
      "TF_HALLOWEEN_DOOMSDAY_WIN_MINIGAMES": 7.5,
      "TF_MVM_MAPS_ROTTENBURG_TANK": 7.5,
      "TF_ENGINEER_DESTROY_STICKIES": 7.5,
      "TF_HALLOWEEN_HELLTOWER_MILESTONE": 7.4,
      "TF_ENGINEER_SENTRY_KILL_LIFETIME_GRIND": 7.4,
      "TF_PYRO_DAMAGE_GRIND": 7.4,
      "TF_SOLDIER_AIRSTRIKE_MAX_CLIP": 7.2,
      "TF_DEMOMAN_DAMAGE_GRIND": 7.2,
      "TF_MAPS_SNAKEWATER_PUSH_BACK_AND_WIN": 7.1,
      "TF_MVM_SCOUT_MARK_FOR_DEATH": 7.1,
      "TF_MVM_USE_BUILD_BOTTLE": 7.1,
      "TF_MAPS_DOOMSDAY_PLAY_EACH_CLASS": 7.1,
      "TF_MAPS_FOUNDRY_WIN_ROUNDS": 7.1,
      "TF_SPY_KILL_BACKSCATTER_SCOUT": 7,
      "TF_DEMOMAN_QUICK_KILLS": 7,
      "TF_MVM_USE_TELEPORT_BOTTLE": 7,
      "TF_MVM_MEDIC_SHARE_BOTTLES": 6.9,
      "TF_MVM_KILL_MEDICS_CHARGED": 6.9,
      "TF_REPLAY_YOUTUBE_VIEWS_TIER3": 6.9,
      "TF_ENGINEER_REPAIR_TEAM_GRIND": 6.9,
      "TF_MVM_ROCKET_SPECIALIST_KILL_GRIND": 6.8,
      "TF_HALLOWEEN_DOOMSDAY_MILESTONE": 6.7,
      "TF_MAPS_SNAKEWATER_TEAM_KILL": 6.7,
      "TF_MVM_DEFEND_CAP": 6.7,
      "TF_MVM_ADVANCED_EARN_ALL_BONUSES": 6.7,
      "TF_PYRO_IGNITE_WITH_RAINBOW": 6.7,
      "TF_MAPS_DOOMSDAY_WIN_ROUNDS": 6.7,
      "TF_REPLAY_YOUTUBE_VIEWS_HIGHEST": 6.7,
      "TF_TAUNT_CONGA_KILL": 6.6,
      "TF_HALLOWEEN_HELLTOWER_KILL_GRIND": 6.6,
      "TF_MVM_DEMO_GROUP_KILL": 6.6,
      "TF_MVM_HEAVY_RAGE_PUSH_DEPLOYING_ROBOT": 6.6,
      "TF_HALLOWEEN_DOOMSDAY_SCORE_GOALS": 6.5,
      "TF_MVM_MAPS_ROTTENBURG_BOMB": 6.5,
      "TF_HALLOWEEN_HELLTOWER_KILL_BROTHERS": 6.5,
      "TF_MVM_PYRO_BOMB_RESET": 6.5,
      "TF_MVM_SPY_SAP_ROBOTS": 6.5,
      "TF_MVM_PLAY_GAME_FRIENDS": 6.5,
      "TF_KILL_BALLOONICORN_OWNERS": 6.5,
      "TF_MVM_MEDIC_REVIVE_TEAMMATES": 6.4,
      "TF_MVM_MAPS_MANNHATTAN_STUN_RADIOWAVE": 6.4,
      "TF_HALLOWEEN_HELLTOWER_SKELETON_GRIND": 6.4,
      "TF_MVM_PLAY_EACH_CLASS": 6.4,
      "TF_HALLOWEEN_DOOMSDAY_RESPAWN_TEAMMATES": 6.3,
      "TF_PARACHUTE_KILL_GRIND": 6.3,
      "TF_MVM_SENTRY_BUSTER_FRIENDLY_FIRE": 6.3,
      "TF_MAPS_SNAKEWATER_DOUBLE_AIR_DEATHS": 6.3,
      "TF_MVM_KILL_ROBOT_MEGA_GRIND": 6.3,
      "TF_MVM_KILL_ROBOT_GRIND": 6.3,
      "TF_MVM_COLLECT_MONEY_GRIND": 6.3,
      "TF_MAPS_POWERHOUSE_PUSH_BACK_AND_WIN": 6.2,
      "TF_MVM_MEDIC_SHIELD_BLOCK_DAMAGE": 6.2,
      "TF_HALLOWEEN_HELLTOWER_ENVIRONMENTAL_KILLS": 6.2,
      "TF_TAUNT_RPS_SCISSORS": 6,
      "TF_TAUNT_RPS_ROCK": 6,
      "TF_HALLOWEEN_HELLTOWER_WIN_ROUNDS": 6,
      "TF_MELEE_KILL_CLASSIC_RIFLE_SNIPER": 5.9,
      "TF_MVM_MAPS_MANNHATTAN_BOMB_BOT_GRIND": 5.9,
      "TF_MVM_MAPS_MANNHATTAN_NO_GATES": 5.9,
      "TF_HALLOWEEN_DOOMSDAY_TINY_SMASHER": 5.8,
      "TF_SOLDIER_PARACHUTE_KILL_GROUP": 5.8,
      "TF_MVM_MAPS_MANNHATTAN_MYSTERY": 5.8,
      "TF_MAPS_SNAKEWATER_KILL_ENEMIES_IN_MIDDLE": 5.8,
      "TF_DEMOMAN_CHARGE_KILL_CHARGING_DEMO": 5.7,
      "TF_SOLDIER_PARACHUTE_KILL_PARACHUTE": 5.7,
      "TF_MVM_SNIPER_COLLECT_HEADSHOT_MONEY": 5.7,
      "TF_MVM_MAPS_MANNHATTAN_PIT": 5.7,
      "TF_MAPS_SNAKEWATER_WIN_ROUNDS": 5.7,
      "TF_MAPS_PROCESS_WIN_ROUNDS": 5.7,
      "TF_MAPS_STANDIN_WIN_ROUNDS": 5.7,
      "TF_SOLDIER_AIRSTRIKE_GROUP_KILL": 5.6,
      "TF_MVM_MAPS_ROTTENBURG_PIT_GRIND": 5.6,
      "TF_PYRO_IGNITE_PLAYER_BEING_FLIPPED": 5.5,
      "TF_SNIPER_CLASSIC_RIFLE_GIB_GRIND": 5.5,
      "TF_SNIPER_CLASSIC_RIFLE_NOSCOPE_HEADSHOT": 5.5,
      "TF_SCOUT_BACKSCATTER_KILL_HEAVY_MEDIC_PAIR": 5.5,
      "TF_TAUNT_WHILE_CAPPING": 5.4,
      "TF_DEMOMAN_PARACHUTE_KILL_PARACHUTE": 5.4,
      "TF_DEMOMAN_PARACHUTE_KILL_GROUP": 5.4,
      "TF_SNIPER_CLASSIC_RIFLE_HEADSHOT_JUMPER": 5.4,
      "TF_HALLOWEEN_DOOMSDAY_KILL_KARTS": 5.3,
      "TF_TAUNT_DOSIDO_MELLE_KILL": 5.3,
      "TF_SCOUT_BACKSCATTER_KILL_SPY_GRIND": 5.3,
      "TF_HALLOWEEN_DOOMSDAY_COLLECT_DUCKS": 5.2,
      "TF_SCOUT_BACKSCATTER_KILL_FRIENDS_GRIND": 5.2,
      "TF_SNIPER_PARACHUTE_GRIND": 5.1,
      "TF_DEMOMAN_PARACHUTE_DISTANCE": 5.1,
      "TF_SOLDIER_PARACHUTE_DISTANCE": 5.1,
      "TF_MAPS_POWERHOUSE_FAST_FINAL_CAP": 4.5,
      "TF_MAPS_POWERHOUSE_KILL_ENEMY_IN_WATER": 4.2,
      "TF_MAPS_POWERHOUSE_KILL_CAPPING_PLAYER": 4,
      "TF_MAPS_POWERHOUSE_WIN_ROUNDS": 3.7,
      "TF_PASS_TIME_HAT": 3,
      "TF_PASS_TIME_GRIND": 2.4
    },
    "271590": {
      "ACH00": 82.2,
      "ACH30": 74.1,
      "ACH49": 51.6,
      "ACHH1": 51,
      "ACH26": 44.3,
      "ACH31": 44.1,
      "ACH05": 42.2,
      "ACH01": 39.6,
      "ACH06": 31.4,
      "ACH32": 30.8,
      "ACHH4": 30.3,
      "ACH39": 30.2,
      "ACH42": 30.1,
      "ACH46": 29.1,
      "ACH02": 28.4,
      "ACHH5": 28,
      "ACH07": 26.9,
      "ACH40": 26,
      "ACHH8": 25.2,
      "ACH28": 25.1,
      "ACH08": 23.8,
      "ACH03": 23.1,
      "ACH04": 22.6,
      "ACH09": 21.8,
      "ACH25": 21,
      "ACHH3": 20.6,
      "ACH33": 20.6,
      "ACHH2": 18.9,
      "ACH41": 18.2,
      "ACH36": 16.5,
      "ACH48": 15.9,
      "ACH24": 14.9,
      "ACH19": 14.7,
      "ACHGO2": 13.5,
      "ACH18": 12.3,
      "ACHGO3": 12,
      "ACHGO1": 11.6,
      "ACH43": 11.6,
      "ACH35": 11.5,
      "ACH12": 10.9,
      "ACHH7": 10.7,
      "ACH14": 10.4,
      "ACH34": 10.3,
      "ACHH10": 10.2,
      "ACH47": 10.2,
      "ACHR4": 10.1,
      "ACH23": 10.1,
      "ACHH6": 10,
      "ACH27": 9.3,
      "ACHGO4": 8.8,
      "ACH51": 8.8,
      "ACHGO6": 7.8,
      "ACH50": 7.5,
      "ACHGO5": 7.3,
      "ACH22": 5.9,
      "ACH29": 5.1,
      "ACH38": 4.9,
      "ACH13": 4.9,
      "ACHR9": 4.8,
      "ACH20": 4.8,
      "ACH15": 4.5,
      "ACH17": 4.4,
      "ACH45": 4.3,
      "ACH16": 4.3,
      "ACH21": 4.1,
      "ACH10": 4.1,
      "ACH11": 3.8,
      "ACHR5": 3.1,
      "ACHH11": 2.9,
      "ACHR10": 2.7,
      "ACHR6": 2.7,
      "ACHR8": 2.5,
      "ACHR7": 2.5,
      "ACHR3": 2.5,
      "ACHR2": 2.5,
      "ACHGO8": 1.9,
      "ACHGO7": 1.9
    }
  }
}